{"_type":"export","__export_format":4,"__export_date":"2020-12-05T02:07:52.031Z","__export_source":"insomnia.desktop.app:v2020.5.1","resources":[{"_id":"req_955fb21c50a2434093d894c2a0e7976b","parentId":"wrk_8cc8c2ca1b2b4ea78b1c50c1cb705ed4","modified":1607128958102,"created":1607127257749,"url":"{{url}}","name":"List","description":"","method":"GET","body":{},"parameters":[],"headers":[],"authentication":{},"metaSortKey":-1607127257749,"isPrivate":false,"settingStoreCookies":true,"settingSendCookies":true,"settingDisableRenderRequestBody":false,"settingEncodeUrl":true,"settingRebuildPath":true,"settingFollowRedirects":"global","_type":"request"},{"_id":"wrk_8cc8c2ca1b2b4ea78b1c50c1cb705ed4","parentId":null,"modified":1607127233966,"created":1607127233966,"name":"Farmacia","description":"","scope":null,"_type":"workspace"},{"_id":"req_8aa0c693b8ab444fb9939281fcb745cc","parentId":"wrk_8cc8c2ca1b2b4ea78b1c50c1cb705ed4","modified":1607128948896,"created":1607127249104,"url":"{{url}}","name":"Create","description":"","method":"POST","body":{"mimeType":"application/json","text":"{\n\t\"nome\": \"William\",\n\t\"cpf\": \"9090\",\n\t\"email\": \"William@gmail.com\",\n\t\"senha\": \"123456789\",\n\t\"telefone\": \"9090\"\n}"},"parameters":[],"headers":[{"name":"Content-Type","value":"application/json","id":"pair_5ec9c9decc9945e3a7b25c955b75d474"}],"authentication":{},"metaSortKey":-1607127249104,"isPrivate":false,"settingStoreCookies":true,"settingSendCookies":true,"settingDisableRenderRequestBody":false,"settingEncodeUrl":true,"settingRebuildPath":true,"settingFollowRedirects":"global","_type":"request"},{"_id":"req_c3a7b2b4bb0a4140b0b7ae5b60522146","parentId":"wrk_8cc8c2ca1b2b4ea78b1c50c1cb705ed4","modified":1607128942592,"created":1607127265581,"url":"{{url}}/5fcad699b7a67c9e06ef0936","name":"Update","description":"","method":"PUT","body":{"mimeType":"application/json","text":"{\n\t\"nome\": \"TutsTuts\",\n\t\"cpf\": \"1111111111\",\n\t\"email\": \"TutsTuts@gmail.com\",\n\t\"senha\": \"090909090\",\n\t\"telefone\": \"999999999999999999999999\"\n}"},"parameters":[],"headers":[{"name":"Content-Type","value":"application/json","id":"pair_0c09fc40eca247cc9790c5ac8f3c7a19"}],"authentication":{},"metaSortKey":-1607127249054,"isPrivate":false,"settingStoreCookies":true,"settingSendCookies":true,"settingDisableRenderRequestBody":false,"settingEncodeUrl":true,"settingRebuildPath":true,"settingFollowRedirects":"global","_type":"request"},{"_id":"req_3a6f09b951934b04877c9aaf83f9fbae","parentId":"wrk_8cc8c2ca1b2b4ea78b1c50c1cb705ed4","modified":1607128930430,"created":1607127306539,"url":"{{url}}/5fcad699b7a67c9e06ef0936","name":"Delete","description":"","method":"DELETE","body":{},"parameters":[],"headers":[],"authentication":{},"metaSortKey":-1607127249004,"isPrivate":false,"settingStoreCookies":true,"settingSendCookies":true,"settingDisableRenderRequestBody":false,"settingEncodeUrl":true,"settingRebuildPath":true,"settingFollowRedirects":"global","_type":"request"},{"_id":"env_4ddd22c2591c86d7fc525080e0c91cfa7a06a4bd","parentId":"wrk_8cc8c2ca1b2b4ea78b1c50c1cb705ed4","modified":1607128936538,"created":1607127234369,"name":"Base Environment","data":{"url":"http://localhost:3333/funcionario"},"dataPropertyOrder":{"&":["url"]},"color":null,"isPrivate":false,"metaSortKey":1607127234369,"_type":"environment"},{"_id":"jar_4ddd22c2591c86d7fc525080e0c91cfa7a06a4bd","parentId":"wrk_8cc8c2ca1b2b4ea78b1c50c1cb705ed4","modified":1607127234378,"created":1607127234378,"name":"Default Jar","cookies":[],"_type":"cookie_jar"},{"_id":"spc_1942902e55444052b6bff1a9b4fde1ac","parentId":"wrk_8cc8c2ca1b2b4ea78b1c50c1cb705ed4","modified":1607127234016,"created":1607127234016,"fileName":"Farmacia","contents":"","contentType":"yaml","_type":"api_spec"}]}